{
	"$schema": "http://schema.management.azure.com/schemas/2015-01-01/deploymentTemplate.json#",
	"contentVersion": "1.0.0.0",
	"parameters": {
		"factoryName": {
			"type": "string",
			"metadata": "Data Factory name",
			"defaultValue": "rohitbigdata3"
		},
		"MySql2_password": {
			"type": "secureString",
			"metadata": "Secure string for 'password' of 'MySql2'"
		},
		"dineshMySql3_password": {
			"type": "secureString",
			"metadata": "Secure string for 'password' of 'dineshMySql3'"
		},
		"dineshnewMySql3_password": {
			"type": "secureString",
			"metadata": "Secure string for 'password' of 'dineshnewMySql3'"
		},
		"MySql2_properties_typeProperties_server": {
			"type": "string",
			"defaultValue": "localhost"
		},
		"MySql2_properties_typeProperties_database": {
			"type": "string",
			"defaultValue": "hospital"
		},
		"MySql2_properties_typeProperties_username": {
			"type": "string",
			"defaultValue": "root"
		},
		"dineshMySql3_properties_typeProperties_server": {
			"type": "string",
			"defaultValue": "localhost"
		},
		"dineshMySql3_properties_typeProperties_database": {
			"type": "string",
			"defaultValue": "healthcare_db"
		},
		"dineshMySql3_properties_typeProperties_username": {
			"type": "string",
			"defaultValue": "root"
		},
		"dineshnewMySql3_properties_typeProperties_server": {
			"type": "string",
			"defaultValue": "localhost"
		},
		"dineshnewMySql3_properties_typeProperties_database": {
			"type": "string",
			"defaultValue": "healthcare_db"
		},
		"dineshnewMySql3_properties_typeProperties_username": {
			"type": "string",
			"defaultValue": "root"
		}
	},
	"variables": {
		"factoryId": "[concat('Microsoft.DataFactory/factories/', parameters('factoryName'))]"
	},
	"resources": [
		{
			"name": "[concat(parameters('factoryName'), '/load_json')]",
			"type": "Microsoft.DataFactory/factories/datasets",
			"apiVersion": "2018-06-01",
			"properties": {
				"linkedServiceName": {
					"referenceName": "helthcare_project_link_service",
					"type": "LinkedServiceReference"
				},
				"annotations": [],
				"type": "Json",
				"typeProperties": {
					"location": {
						"type": "AzureBlobFSLocation",
						"folderPath": "landing-data/json-file-data",
						"fileSystem": "healthcare-project-data"
					}
				},
				"schema": {
					"type": "object",
					"properties": {
						"resourceType": {
							"type": "string"
						},
						"type": {
							"type": "string"
						},
						"entry": {
							"type": "array",
							"items": {
								"type": "object",
								"properties": {
									"fullUrl": {
										"type": "string"
									},
									"resource": {
										"type": "object",
										"properties": {
											"resourceType": {
												"type": "string"
											},
											"id": {
												"type": "string"
											},
											"meta": {
												"type": "object",
												"properties": {
													"profile": {
														"type": "array",
														"items": {
															"type": "string"
														}
													}
												}
											},
											"text": {
												"type": "object",
												"properties": {
													"status": {
														"type": "string"
													},
													"div": {
														"type": "string"
													}
												}
											},
											"extension": {
												"type": "array",
												"items": {
													"type": "object",
													"properties": {
														"url": {
															"type": "string"
														},
														"extension": {
															"type": "array",
															"items": {
																"type": "object",
																"properties": {
																	"url": {
																		"type": "string"
																	},
																	"valueCoding": {
																		"type": "object",
																		"properties": {
																			"system": {
																				"type": "string"
																			},
																			"code": {
																				"type": "string"
																			},
																			"display": {
																				"type": "string"
																			}
																		}
																	}
																}
															}
														}
													}
												}
											},
											"identifier": {
												"type": "array",
												"items": {
													"type": "object",
													"properties": {
														"system": {
															"type": "string"
														},
														"value": {
															"type": "string"
														}
													}
												}
											},
											"name": {
												"type": "array",
												"items": {
													"type": "object",
													"properties": {
														"use": {
															"type": "string"
														},
														"family": {
															"type": "string"
														},
														"given": {
															"type": "array",
															"items": {
																"type": "string"
															}
														},
														"prefix": {
															"type": "array",
															"items": {
																"type": "string"
															}
														}
													}
												}
											},
											"telecom": {
												"type": "array",
												"items": {
													"type": "object",
													"properties": {
														"system": {
															"type": "string"
														},
														"value": {
															"type": "string"
														},
														"use": {
															"type": "string"
														}
													}
												}
											},
											"gender": {
												"type": "string"
											},
											"birthDate": {
												"type": "string"
											},
											"deceasedDateTime": {
												"type": "string"
											},
											"address": {
												"type": "array",
												"items": {
													"type": "object",
													"properties": {
														"extension": {
															"type": "array",
															"items": {
																"type": "object",
																"properties": {
																	"url": {
																		"type": "string"
																	},
																	"extension": {
																		"type": "array",
																		"items": {
																			"type": "object",
																			"properties": {
																				"url": {
																					"type": "string"
																				},
																				"valueDecimal": {
																					"type": "number"
																				}
																			}
																		}
																	}
																}
															}
														},
														"line": {
															"type": "array",
															"items": {
																"type": "string"
															}
														},
														"city": {
															"type": "string"
														},
														"state": {
															"type": "string"
														},
														"postalCode": {
															"type": "string"
														},
														"country": {
															"type": "string"
														}
													}
												}
											},
											"maritalStatus": {
												"type": "object",
												"properties": {
													"coding": {
														"type": "array",
														"items": {
															"type": "object",
															"properties": {
																"system": {
																	"type": "string"
																},
																"code": {
																	"type": "string"
																},
																"display": {
																	"type": "string"
																}
															}
														}
													},
													"text": {
														"type": "string"
													}
												}
											},
											"multipleBirthBoolean": {
												"type": "boolean"
											},
											"communication": {
												"type": "array",
												"items": {
													"type": "object",
													"properties": {
														"language": {
															"type": "object",
															"properties": {
																"coding": {
																	"type": "array",
																	"items": {
																		"type": "object",
																		"properties": {
																			"system": {
																				"type": "string"
																			},
																			"code": {
																				"type": "string"
																			},
																			"display": {
																				"type": "string"
																			}
																		}
																	}
																},
																"text": {
																	"type": "string"
																}
															}
														}
													}
												}
											}
										}
									},
									"request": {
										"type": "object",
										"properties": {
											"method": {
												"type": "string"
											},
											"url": {
												"type": "string"
											}
										}
									}
								}
							}
						}
					}
				}
			},
			"dependsOn": []
		},
		{
			"name": "[concat(parameters('factoryName'), '/load_mup_file')]",
			"type": "Microsoft.DataFactory/factories/datasets",
			"apiVersion": "2018-06-01",
			"properties": {
				"linkedServiceName": {
					"referenceName": "helthcare_project_link_service",
					"type": "LinkedServiceReference"
				},
				"annotations": [],
				"type": "DelimitedText",
				"typeProperties": {
					"location": {
						"type": "AzureBlobFSLocation",
						"fileName": "MUP_DPR_RY24_P04_V10_DY22_NPIBN - MUP_DPR_RY24_P04_V10_DY22_NPIBN (1).csv",
						"folderPath": "landing-data/mup-csv-file-data",
						"fileSystem": "healthcare-project-data"
					},
					"columnDelimiter": ",",
					"escapeChar": "\\",
					"firstRowAsHeader": true,
					"quoteChar": "\""
				},
				"schema": [
					{
						"name": "Prscrbr_NPI",
						"type": "String"
					},
					{
						"name": "Prscrbr_Last_Org_Name",
						"type": "String"
					},
					{
						"name": "Prscrbr_First_Name",
						"type": "String"
					},
					{
						"name": "Prscrbr_City",
						"type": "String"
					},
					{
						"name": "Prscrbr_State_Abrvtn",
						"type": "String"
					},
					{
						"name": "Prscrbr_State_FIPS",
						"type": "String"
					},
					{
						"name": "Prscrbr_Type",
						"type": "String"
					},
					{
						"name": "Prscrbr_Type_Src",
						"type": "String"
					},
					{
						"name": "Brnd_Name",
						"type": "String"
					},
					{
						"name": "Gnrc_Name",
						"type": "String"
					},
					{
						"name": "Tot_Clms",
						"type": "String"
					},
					{
						"name": "Tot_30day_Fills",
						"type": "String"
					},
					{
						"name": "Tot_Day_Suply",
						"type": "String"
					},
					{
						"name": "Tot_Drug_Cst",
						"type": "String"
					},
					{
						"name": "Tot_Benes",
						"type": "String"
					},
					{
						"name": "GE65_Sprsn_Flag",
						"type": "String"
					},
					{
						"name": "GE65_Tot_Clms",
						"type": "String"
					},
					{
						"name": "GE65_Tot_30day_Fills",
						"type": "String"
					},
					{
						"name": "GE65_Tot_Drug_Cst",
						"type": "String"
					},
					{
						"name": "GE65_Tot_Day_Suply",
						"type": "String"
					},
					{
						"name": "GE65_Bene_Sprsn_Flag",
						"type": "String"
					},
					{
						"name": "GE65_Tot_Benes",
						"type": "String"
					}
				]
			},
			"dependsOn": []
		},
		{
			"name": "[concat(parameters('factoryName'), '/mup_sink_file')]",
			"type": "Microsoft.DataFactory/factories/datasets",
			"apiVersion": "2018-06-01",
			"properties": {
				"linkedServiceName": {
					"referenceName": "helthcare_project_link_service",
					"type": "LinkedServiceReference"
				},
				"annotations": [],
				"type": "DelimitedText",
				"typeProperties": {
					"location": {
						"type": "AzureBlobFSLocation",
						"folderPath": "bronze-layer/mup-drug-spent",
						"fileSystem": "healthcare-project-data"
					},
					"columnDelimiter": ",",
					"escapeChar": "\\",
					"firstRowAsHeader": true,
					"quoteChar": "\""
				},
				"schema": []
			},
			"dependsOn": []
		},
		{
			"name": "[concat(parameters('factoryName'), '/mup_table_load')]",
			"type": "Microsoft.DataFactory/factories/datasets",
			"apiVersion": "2018-06-01",
			"properties": {
				"linkedServiceName": {
					"referenceName": "MySql1",
					"type": "LinkedServiceReference"
				},
				"annotations": [],
				"type": "MySqlTable",
				"schema": [],
				"typeProperties": {
					"tableName": "mup_detail"
				}
			},
			"dependsOn": []
		},
		{
			"name": "[concat(parameters('factoryName'), '/shink_json')]",
			"type": "Microsoft.DataFactory/factories/datasets",
			"apiVersion": "2018-06-01",
			"properties": {
				"linkedServiceName": {
					"referenceName": "helthcare_project_link_service",
					"type": "LinkedServiceReference"
				},
				"annotations": [],
				"type": "Json",
				"typeProperties": {
					"location": {
						"type": "AzureBlobFSLocation",
						"folderPath": "bronze-layer/patient-fhir",
						"fileSystem": "healthcare-project-data"
					}
				},
				"schema": {}
			},
			"dependsOn": []
		},
		{
			"name": "[concat(parameters('factoryName'), '/sink_hospital_cost')]",
			"type": "Microsoft.DataFactory/factories/datasets",
			"apiVersion": "2018-06-01",
			"properties": {
				"linkedServiceName": {
					"referenceName": "helthcare_project_link_service",
					"type": "LinkedServiceReference"
				},
				"annotations": [],
				"type": "DelimitedText",
				"typeProperties": {
					"location": {
						"type": "AzureBlobFSLocation",
						"folderPath": "bronze-layer/hospital-cost",
						"fileSystem": "healthcare-project-data"
					},
					"columnDelimiter": ",",
					"escapeChar": "\\",
					"firstRowAsHeader": true,
					"quoteChar": "\""
				},
				"schema": []
			},
			"dependsOn": []
		},
		{
			"name": "[concat(parameters('factoryName'), '/sink_icd_file')]",
			"type": "Microsoft.DataFactory/factories/datasets",
			"apiVersion": "2018-06-01",
			"properties": {
				"linkedServiceName": {
					"referenceName": "helthcare_project_link_service",
					"type": "LinkedServiceReference"
				},
				"annotations": [],
				"type": "DelimitedText",
				"typeProperties": {
					"location": {
						"type": "AzureBlobFSLocation",
						"folderPath": "bronze-layer/icd10",
						"fileSystem": "healthcare-project-data"
					},
					"columnDelimiter": "\t",
					"rowDelimiter": "\n",
					"escapeChar": "\\",
					"firstRowAsHeader": false,
					"quoteChar": "\""
				},
				"schema": []
			},
			"dependsOn": []
		},
		{
			"name": "[concat(parameters('factoryName'), '/to_csv')]",
			"type": "Microsoft.DataFactory/factories/datasets",
			"apiVersion": "2018-06-01",
			"properties": {
				"linkedServiceName": {
					"referenceName": "new_practice",
					"type": "LinkedServiceReference"
				},
				"annotations": [],
				"type": "DelimitedText",
				"typeProperties": {
					"location": {
						"type": "AzureBlobFSLocation",
						"fileName": "REDBUS_FINAL - REDBUS_FINAL.csv",
						"folderPath": "to_csv",
						"fileSystem": "june-paractis"
					},
					"columnDelimiter": ",",
					"escapeChar": "\\",
					"firstRowAsHeader": true,
					"quoteChar": "\""
				},
				"schema": [
					{
						"name": "First_Name",
						"type": "String"
					},
					{
						"name": "Last_Name",
						"type": "String"
					},
					{
						"name": "Age",
						"type": "String"
					},
					{
						"name": "City_From",
						"type": "String"
					},
					{
						"name": "City To",
						"type": "String"
					},
					{
						"name": "Bus_Type",
						"type": "String"
					},
					{
						"name": "Seat_Type",
						"type": "String"
					},
					{
						"name": "Booking_Type",
						"type": "String"
					},
					{
						"name": "Payment_Method",
						"type": "String"
					},
					{
						"name": "Ticket_Fare",
						"type": "String"
					}
				]
			},
			"dependsOn": []
		},
		{
			"name": "[concat(parameters('factoryName'), '/to_csv1')]",
			"type": "Microsoft.DataFactory/factories/datasets",
			"apiVersion": "2018-06-01",
			"properties": {
				"linkedServiceName": {
					"referenceName": "new_practice",
					"type": "LinkedServiceReference"
				},
				"annotations": [],
				"type": "DelimitedText",
				"typeProperties": {
					"location": {
						"type": "AzureBlobFSLocation",
						"fileName": "pos_batch_sep_dec - pos_batch_sep_dec.csv",
						"folderPath": "to_csv",
						"fileSystem": "june-paractis"
					},
					"columnDelimiter": ",",
					"escapeChar": "\\",
					"firstRowAsHeader": true,
					"quoteChar": "\""
				},
				"schema": [
					{
						"name": "transaction_id",
						"type": "String"
					},
					{
						"name": "store_id",
						"type": "String"
					},
					{
						"name": "store_name",
						"type": "String"
					},
					{
						"name": "store_city",
						"type": "String"
					},
					{
						"name": "store_region",
						"type": "String"
					},
					{
						"name": "cashier_id",
						"type": "String"
					},
					{
						"name": "customer_id",
						"type": "String"
					},
					{
						"name": "transaction_date",
						"type": "String"
					},
					{
						"name": "transaction_time",
						"type": "String"
					},
					{
						"name": "product_sku",
						"type": "String"
					},
					{
						"name": "product_name",
						"type": "String"
					},
					{
						"name": "category",
						"type": "String"
					},
					{
						"name": "subcategory",
						"type": "String"
					},
					{
						"name": "quantity",
						"type": "String"
					},
					{
						"name": "unit_price",
						"type": "String"
					},
					{
						"name": "discount_pct",
						"type": "String"
					},
					{
						"name": "total_amount",
						"type": "String"
					},
					{
						"name": "payment_method",
						"type": "String"
					},
					{
						"name": "loyalty_points",
						"type": "String"
					}
				]
			},
			"dependsOn": []
		},
		{
			"name": "[concat(parameters('factoryName'), '/txt_file_load')]",
			"type": "Microsoft.DataFactory/factories/datasets",
			"apiVersion": "2018-06-01",
			"properties": {
				"linkedServiceName": {
					"referenceName": "helthcare_project_link_service",
					"type": "LinkedServiceReference"
				},
				"annotations": [],
				"type": "DelimitedText",
				"typeProperties": {
					"location": {
						"type": "AzureBlobFSLocation",
						"fileName": "icd10cm_codes_2025 (1) (1).txt",
						"folderPath": "landing-data/text-file-data",
						"fileSystem": "healthcare-project-data"
					},
					"columnDelimiter": "\t",
					"rowDelimiter": "\n",
					"escapeChar": "\\",
					"firstRowAsHeader": false,
					"quoteChar": "\""
				},
				"schema": [
					{
						"name": "A000        Cholera due to Vibrio cholerae 01",
						"type": "String"
					},
					{
						"name": " biovar cholerae",
						"type": "String"
					}
				]
			},
			"dependsOn": []
		},
		{
			"name": "[concat(parameters('factoryName'), '/MySql2')]",
			"type": "Microsoft.DataFactory/factories/linkedServices",
			"apiVersion": "2018-06-01",
			"properties": {
				"annotations": [],
				"type": "MySql",
				"typeProperties": {
					"server": "[parameters('MySql2_properties_typeProperties_server')]",
					"port": 3306,
					"database": "[parameters('MySql2_properties_typeProperties_database')]",
					"username": "[parameters('MySql2_properties_typeProperties_username')]",
					"sslMode": 1,
					"useSystemTrustStore": 0,
					"password": {
						"type": "SecureString",
						"value": "[parameters('MySql2_password')]"
					},
					"driverVersion": "v2"
				},
				"connectVia": {
					"referenceName": "integrationRuntime2",
					"type": "IntegrationRuntimeReference"
				}
			},
			"dependsOn": []
		},
		{
			"name": "[concat(parameters('factoryName'), '/dineshMySql3')]",
			"type": "Microsoft.DataFactory/factories/linkedServices",
			"apiVersion": "2018-06-01",
			"properties": {
				"annotations": [],
				"type": "MySql",
				"typeProperties": {
					"server": "[parameters('dineshMySql3_properties_typeProperties_server')]",
					"port": 3306,
					"database": "[parameters('dineshMySql3_properties_typeProperties_database')]",
					"username": "[parameters('dineshMySql3_properties_typeProperties_username')]",
					"sslMode": 1,
					"useSystemTrustStore": 0,
					"password": {
						"type": "SecureString",
						"value": "[parameters('dineshMySql3_password')]"
					},
					"driverVersion": "v2"
				},
				"connectVia": {
					"referenceName": "integrationRuntime2",
					"type": "IntegrationRuntimeReference"
				}
			},
			"dependsOn": []
		},
		{
			"name": "[concat(parameters('factoryName'), '/dineshnewMySql3')]",
			"type": "Microsoft.DataFactory/factories/linkedServices",
			"apiVersion": "2018-06-01",
			"properties": {
				"annotations": [],
				"type": "MySql",
				"typeProperties": {
					"server": "[parameters('dineshnewMySql3_properties_typeProperties_server')]",
					"port": 3306,
					"database": "[parameters('dineshnewMySql3_properties_typeProperties_database')]",
					"username": "[parameters('dineshnewMySql3_properties_typeProperties_username')]",
					"sslMode": 1,
					"useSystemTrustStore": 0,
					"password": {
						"type": "SecureString",
						"value": "[parameters('dineshnewMySql3_password')]"
					},
					"driverVersion": "v2"
				},
				"connectVia": {
					"referenceName": "integrationRuntime2",
					"type": "IntegrationRuntimeReference"
				}
			},
			"dependsOn": []
		},
		{
			"name": "[concat(parameters('factoryName'), '/csv_to_parquet_to_synaps')]",
			"type": "Microsoft.DataFactory/factories/pipelines",
			"apiVersion": "2018-06-01",
			"properties": {
				"activities": [
					{
						"name": "Copy data1",
						"type": "Copy",
						"dependsOn": [],
						"policy": {
							"timeout": "0.12:00:00",
							"retry": 0,
							"retryIntervalInSeconds": 30,
							"secureOutput": false,
							"secureInput": false
						},
						"userProperties": [],
						"typeProperties": {
							"source": {
								"type": "DelimitedTextSource",
								"storeSettings": {
									"type": "AzureBlobFSReadSettings",
									"recursive": true,
									"enablePartitionDiscovery": false
								},
								"formatSettings": {
									"type": "DelimitedTextReadSettings"
								}
							},
							"sink": {
								"type": "ParquetSink",
								"storeSettings": {
									"type": "AzureBlobFSWriteSettings",
									"copyBehavior": "PreserveHierarchy"
								},
								"formatSettings": {
									"type": "ParquetWriteSettings"
								}
							},
							"enableStaging": false,
							"translator": {
								"type": "TabularTranslator",
								"typeConversion": true,
								"typeConversionSettings": {
									"allowDataTruncation": true,
									"treatBooleanAsNumber": false
								}
							}
						},
						"inputs": [
							{
								"referenceName": "to_csv1",
								"type": "DatasetReference",
								"parameters": {}
							}
						],
						"outputs": [
							{
								"referenceName": "Parquet1",
								"type": "DatasetReference",
								"parameters": {}
							}
						]
					},
					{
						"name": "Copy data2",
						"type": "Copy",
						"dependsOn": [
							{
								"activity": "Copy data1",
								"dependencyConditions": [
									"Succeeded"
								]
							}
						],
						"policy": {
							"timeout": "0.12:00:00",
							"retry": 0,
							"retryIntervalInSeconds": 30,
							"secureOutput": false,
							"secureInput": false
						},
						"userProperties": [],
						"typeProperties": {
							"source": {
								"type": "ParquetSource",
								"storeSettings": {
									"type": "AzureBlobFSReadSettings",
									"recursive": true,
									"enablePartitionDiscovery": false
								},
								"formatSettings": {
									"type": "ParquetReadSettings"
								}
							},
							"sink": {
								"type": "SqlDWSink",
								"writeBehavior": "Insert"
							},
							"enableStaging": false,
							"translator": {
								"type": "TabularTranslator",
								"typeConversion": true,
								"typeConversionSettings": {
									"allowDataTruncation": true,
									"treatBooleanAsNumber": false
								}
							}
						},
						"inputs": [
							{
								"referenceName": "Parquet2",
								"type": "DatasetReference",
								"parameters": {}
							}
						],
						"outputs": [
							{
								"referenceName": "in_synaps",
								"type": "DatasetReference",
								"parameters": {}
							}
						]
					}
				],
				"policy": {
					"elapsedTimeMetric": {}
				},
				"annotations": [],
				"lastPublishTime": "2026-06-27T11:33:51Z"
			},
			"dependsOn": [
				"[concat(variables('factoryId'), '/datasets/to_csv1')]"
			]
		},
		{
			"name": "[concat(parameters('factoryName'), '/load_hospital_cost')]",
			"type": "Microsoft.DataFactory/factories/pipelines",
			"apiVersion": "2018-06-01",
			"properties": {
				"activities": [
					{
						"name": "Get Metadata1",
						"type": "GetMetadata",
						"dependsOn": [],
						"policy": {
							"timeout": "0.12:00:00",
							"retry": 0,
							"retryIntervalInSeconds": 30,
							"secureOutput": false,
							"secureInput": false
						},
						"userProperties": [],
						"typeProperties": {
							"dataset": {
								"referenceName": "load_hospital_cost",
								"type": "DatasetReference",
								"parameters": {}
							},
							"fieldList": [
								"childItems"
							],
							"storeSettings": {
								"type": "AzureBlobFSReadSettings",
								"recursive": true,
								"enablePartitionDiscovery": false
							},
							"formatSettings": {
								"type": "DelimitedTextReadSettings"
							}
						}
					},
					{
						"name": "ForEach1",
						"type": "ForEach",
						"dependsOn": [
							{
								"activity": "Get Metadata1",
								"dependencyConditions": [
									"Succeeded"
								]
							}
						],
						"userProperties": [],
						"typeProperties": {
							"items": {
								"value": "@activity('Get Metadata1').output.childItems",
								"type": "Expression"
							},
							"activities": [
								{
									"name": "Copy data1",
									"type": "Copy",
									"dependsOn": [],
									"policy": {
										"timeout": "0.12:00:00",
										"retry": 0,
										"retryIntervalInSeconds": 30,
										"secureOutput": false,
										"secureInput": false
									},
									"userProperties": [],
									"typeProperties": {
										"source": {
											"type": "DelimitedTextSource",
											"storeSettings": {
												"type": "AzureBlobFSReadSettings",
												"recursive": true,
												"wildcardFileName": {
													"value": "@item().name",
													"type": "Expression"
												},
												"enablePartitionDiscovery": false
											},
											"formatSettings": {
												"type": "DelimitedTextReadSettings"
											}
										},
										"sink": {
											"type": "DelimitedTextSink",
											"storeSettings": {
												"type": "AzureBlobFSWriteSettings"
											},
											"formatSettings": {
												"type": "DelimitedTextWriteSettings",
												"quoteAllText": true,
												"fileExtension": ".txt"
											}
										},
										"enableStaging": false,
										"translator": {
											"type": "TabularTranslator",
											"typeConversion": true,
											"typeConversionSettings": {
												"allowDataTruncation": true,
												"treatBooleanAsNumber": false
											}
										}
									},
									"inputs": [
										{
											"referenceName": "load_hospital_cost",
											"type": "DatasetReference",
											"parameters": {}
										}
									],
									"outputs": [
										{
											"referenceName": "sink_hospital_cost",
											"type": "DatasetReference",
											"parameters": {}
										}
									]
								}
							]
						}
					}
				],
				"policy": {
					"elapsedTimeMetric": {}
				},
				"folder": {
					"name": "Healthcare_Data_piplines/landing-folder-to-bronze-load-pipline"
				},
				"annotations": []
			},
			"dependsOn": [
				"[concat(variables('factoryId'), '/datasets/sink_hospital_cost')]"
			]
		},
		{
			"name": "[concat(parameters('factoryName'), '/load_icd_file_in_bronze')]",
			"type": "Microsoft.DataFactory/factories/pipelines",
			"apiVersion": "2018-06-01",
			"properties": {
				"activities": [
					{
						"name": "Copy data1",
						"type": "Copy",
						"dependsOn": [],
						"policy": {
							"timeout": "0.12:00:00",
							"retry": 0,
							"retryIntervalInSeconds": 30,
							"secureOutput": false,
							"secureInput": false
						},
						"userProperties": [],
						"typeProperties": {
							"source": {
								"type": "DelimitedTextSource",
								"storeSettings": {
									"type": "AzureBlobFSReadSettings",
									"recursive": true,
									"enablePartitionDiscovery": false
								},
								"formatSettings": {
									"type": "DelimitedTextReadSettings"
								}
							},
							"sink": {
								"type": "DelimitedTextSink",
								"storeSettings": {
									"type": "AzureBlobFSWriteSettings"
								},
								"formatSettings": {
									"type": "DelimitedTextWriteSettings",
									"quoteAllText": true,
									"fileExtension": ".txt"
								}
							},
							"enableStaging": false,
							"translator": {
								"type": "TabularTranslator",
								"typeConversion": true,
								"typeConversionSettings": {
									"allowDataTruncation": true,
									"treatBooleanAsNumber": false
								}
							}
						},
						"inputs": [
							{
								"referenceName": "txt_file_load",
								"type": "DatasetReference",
								"parameters": {}
							}
						],
						"outputs": [
							{
								"referenceName": "sink_icd_file",
								"type": "DatasetReference",
								"parameters": {}
							}
						]
					}
				],
				"policy": {
					"elapsedTimeMetric": {}
				},
				"folder": {
					"name": "Healthcare_Data_piplines/landing-folder-to-bronze-load-pipline"
				},
				"annotations": []
			},
			"dependsOn": [
				"[concat(variables('factoryId'), '/datasets/txt_file_load')]",
				"[concat(variables('factoryId'), '/datasets/sink_icd_file')]"
			]
		},
		{
			"name": "[concat(parameters('factoryName'), '/load_json_in_bronze')]",
			"type": "Microsoft.DataFactory/factories/pipelines",
			"apiVersion": "2018-06-01",
			"properties": {
				"activities": [
					{
						"name": "Get Metadata1",
						"type": "GetMetadata",
						"dependsOn": [],
						"policy": {
							"timeout": "0.12:00:00",
							"retry": 0,
							"retryIntervalInSeconds": 30,
							"secureOutput": false,
							"secureInput": false
						},
						"userProperties": [],
						"typeProperties": {
							"dataset": {
								"referenceName": "load_json",
								"type": "DatasetReference",
								"parameters": {}
							},
							"fieldList": [
								"childItems"
							],
							"storeSettings": {
								"type": "AzureBlobFSReadSettings",
								"recursive": true,
								"enablePartitionDiscovery": false
							},
							"formatSettings": {
								"type": "JsonReadSettings"
							}
						}
					},
					{
						"name": "ForEach1",
						"type": "ForEach",
						"dependsOn": [
							{
								"activity": "Get Metadata1",
								"dependencyConditions": [
									"Succeeded"
								]
							}
						],
						"userProperties": [],
						"typeProperties": {
							"items": {
								"value": "@activity('Get Metadata1').output.childItems",
								"type": "Expression"
							},
							"activities": [
								{
									"name": "Copy data1",
									"type": "Copy",
									"dependsOn": [],
									"policy": {
										"timeout": "0.12:00:00",
										"retry": 0,
										"retryIntervalInSeconds": 30,
										"secureOutput": false,
										"secureInput": false
									},
									"userProperties": [],
									"typeProperties": {
										"source": {
											"type": "JsonSource",
											"storeSettings": {
												"type": "AzureBlobFSReadSettings",
												"recursive": true,
												"wildcardFileName": {
													"value": "@item().name",
													"type": "Expression"
												},
												"enablePartitionDiscovery": false
											},
											"formatSettings": {
												"type": "JsonReadSettings"
											}
										},
										"sink": {
											"type": "JsonSink",
											"storeSettings": {
												"type": "AzureBlobFSWriteSettings"
											},
											"formatSettings": {
												"type": "JsonWriteSettings"
											}
										},
										"enableStaging": false
									},
									"inputs": [
										{
											"referenceName": "load_json",
											"type": "DatasetReference",
											"parameters": {}
										}
									],
									"outputs": [
										{
											"referenceName": "shink_json",
											"type": "DatasetReference",
											"parameters": {}
										}
									]
								}
							]
						}
					}
				],
				"policy": {
					"elapsedTimeMetric": {}
				},
				"folder": {
					"name": "Healthcare_Data_piplines/landing-folder-to-bronze-load-pipline"
				},
				"annotations": []
			},
			"dependsOn": [
				"[concat(variables('factoryId'), '/datasets/load_json')]",
				"[concat(variables('factoryId'), '/datasets/shink_json')]"
			]
		},
		{
			"name": "[concat(parameters('factoryName'), '/load_mup_drug_spend')]",
			"type": "Microsoft.DataFactory/factories/pipelines",
			"apiVersion": "2018-06-01",
			"properties": {
				"activities": [
					{
						"name": "Copy data1",
						"type": "Copy",
						"dependsOn": [],
						"policy": {
							"timeout": "0.12:00:00",
							"retry": 0,
							"retryIntervalInSeconds": 30,
							"secureOutput": false,
							"secureInput": false
						},
						"userProperties": [],
						"typeProperties": {
							"source": {
								"type": "DelimitedTextSource",
								"storeSettings": {
									"type": "AzureBlobFSReadSettings",
									"recursive": true,
									"enablePartitionDiscovery": false
								},
								"formatSettings": {
									"type": "DelimitedTextReadSettings"
								}
							},
							"sink": {
								"type": "DelimitedTextSink",
								"storeSettings": {
									"type": "AzureBlobFSWriteSettings"
								},
								"formatSettings": {
									"type": "DelimitedTextWriteSettings",
									"quoteAllText": true,
									"fileExtension": ".txt"
								}
							},
							"enableStaging": false,
							"translator": {
								"type": "TabularTranslator",
								"typeConversion": true,
								"typeConversionSettings": {
									"allowDataTruncation": true,
									"treatBooleanAsNumber": false
								}
							}
						},
						"inputs": [
							{
								"referenceName": "load_mup_file",
								"type": "DatasetReference",
								"parameters": {}
							}
						],
						"outputs": [
							{
								"referenceName": "mup_sink_file",
								"type": "DatasetReference",
								"parameters": {}
							}
						]
					}
				],
				"policy": {
					"elapsedTimeMetric": {}
				},
				"folder": {
					"name": "Healthcare_Data_piplines/landing-folder-to-bronze-load-pipline"
				},
				"annotations": []
			},
			"dependsOn": [
				"[concat(variables('factoryId'), '/datasets/load_mup_file')]",
				"[concat(variables('factoryId'), '/datasets/mup_sink_file')]"
			]
		},
		{
			"name": "[concat(parameters('factoryName'), '/MySqlTable1')]",
			"type": "Microsoft.DataFactory/factories/datasets",
			"apiVersion": "2018-06-01",
			"properties": {
				"linkedServiceName": {
					"referenceName": "dineshnewMySql3",
					"type": "LinkedServiceReference"
				},
				"annotations": [],
				"type": "MySqlTable",
				"schema": [],
				"typeProperties": {
					"tableName": "`mup_dpr_report_mysql`"
				}
			},
			"dependsOn": [
				"[concat(variables('factoryId'), '/linkedServices/dineshnewMySql3')]"
			]
		},
		{
			"name": "[concat(parameters('factoryName'), '/MySqltoload')]",
			"type": "Microsoft.DataFactory/factories/datasets",
			"apiVersion": "2018-06-01",
			"properties": {
				"linkedServiceName": {
					"referenceName": "MySql2",
					"type": "LinkedServiceReference"
				},
				"annotations": [],
				"type": "MySqlTable",
				"schema": [],
				"typeProperties": {
					"tableName": "mup_dpr_report_mysql "
				}
			},
			"dependsOn": [
				"[concat(variables('factoryId'), '/linkedServices/MySql2')]"
			]
		}
	]
}